simple_elastic/__init__.py
simple_elastic/cluster.py
simple_elastic/index.py
simple_elastic-2.2.0.dist-info/LICENSE
simple_elastic-2.2.0.dist-info/METADATA
simple_elastic-2.2.0.dist-info/WHEEL
simple_elastic-2.2.0.dist-info/top_level.txt
simple_elastic-2.2.0.dist-info/RECORD
