Metadata-Version: 2.1
Name: simple-elastic
Version: 2.2.0
Summary: A simple wrapper for the elasticsearch package.
Home-page: https://github.com/UB-UNIBAS/simple-elastic
Author: Jonas Waeber
Author-email: jonaswaeber@gmail.com
License: MIT
Download-URL: https://github.com/UB-UNIBAS/simple-elastic/archive/v2.2.0.tar.gz
Keywords: elasticsearch,elastic
Platform: UNKNOWN
License-File: LICENSE
Requires-Dist: elasticsearch7
